LICENSE.TXT
MANIFEST.in
README.md
setup.cfg
setup.py
versioneer.py
pygenes/_version.py
pygenes/pygenes.cpp
pygenes.egg-info/PKG-INFO
pygenes.egg-info/SOURCES.txt
pygenes.egg-info/dependency_links.txt
pygenes.egg-info/top_level.txt
src/genemodels.cpp
src/IntervalTree/IntervalTree.h
src/IntervalTree/LICENSE
src/IntervalTree/Makefile
src/IntervalTree/README
src/IntervalTree/interval_tree_test.cpp