Metadata-Version: 1.0
Name: pygenes
Version: 0.0.5.post3
Summary: In memory gene database searchable using an interval tree
Home-page: UNKNOWN
Author: Andrew McPherson
Author-email: andrew.mcpherson@gmail.com
License: UNKNOWN
Keywords: bioinformatics
Platform: UNKNOWN
